ditch/__init__.py
tests/__init__.py
tests/conftest.py
tests/test_unit.py
ditch-0.0.1.dist-info/LICENSE
ditch-0.0.1.dist-info/METADATA
ditch-0.0.1.dist-info/WHEEL
ditch-0.0.1.dist-info/top_level.txt
ditch-0.0.1.dist-info/RECORD
