Metadata-Version: 2.1
Name: ditch
Version: 0.0.1
Summary: programming resources
Home-page: UNKNOWN
Author: pnowk
Author-email: pnowk123@gmail.com
License: MIT
Keywords: python
Platform: UNKNOWN
Classifier: Development Status :: 3 - Alpha
Classifier: Intended Audience :: Developers
Classifier: License :: OSI Approved :: MIT License
Classifier: Programming Language :: Python :: 3
